pypool/__init__.py
pypool/pool.py
pypool/py.typed
pypool3-0.0.4.dist-info/LICENSE
pypool3-0.0.4.dist-info/METADATA
pypool3-0.0.4.dist-info/WHEEL
pypool3-0.0.4.dist-info/top_level.txt
pypool3-0.0.4.dist-info/RECORD
