Metadata-Version: 2.1
Name: pypool3
Version: 0.0.4
Summary: An extensive python resource pool implementation
Author-email: Andrew C Scott <imgurbot12@gmail.com>
License: The MIT License (MIT)
Project-URL: Repository, https://github.com/imgurbot12/pydns
Keywords: pool,resource-pool,connection-pool
Classifier: Typing :: Typed
Classifier: License :: OSI Approved :: MIT License
Classifier: Intended Audience :: Developers
Classifier: Operating System :: OS Independent
Classifier: Programming Language :: Python :: 3
Classifier: Programming Language :: Python :: 3 :: Only
Classifier: Programming Language :: Python :: 3.8
Classifier: Programming Language :: Python :: 3.9
Classifier: Programming Language :: Python :: 3.10
Classifier: Programming Language :: Python :: 3.11
Classifier: Programming Language :: Python :: 3.12
Classifier: Programming Language :: Python :: 3.13
Requires-Python: >=3.8
License-File: LICENSE
Requires-Dist: typing-extensions>=4.7.1
